README.md
setup.py
artifact_py/__init__.py
artifact_py/__main__.py
artifact_py/artifact.py
artifact_py/code.py
artifact_py/completion.py
artifact_py/dump.py
artifact_py/load.py
artifact_py/name.py
artifact_py/project.py
artifact_py/settings.py
artifact_py/utils.py
artifact_py.egg-info/PKG-INFO
artifact_py.egg-info/SOURCES.txt
artifact_py.egg-info/dependency_links.txt
artifact_py.egg-info/not-zip-safe
artifact_py.egg-info/requires.txt
artifact_py.egg-info/top_level.txt
artifact_py/bin/artifact_py